pymade/__init__.py
pymade/docstrings.json
pymade/pymaker.py
pymade/settings.py
pymade-0.0.1.dist-info/entry_points.txt
pymade-0.0.1.dist-info/LICENSE
pymade-0.0.1.dist-info/WHEEL
pymade-0.0.1.dist-info/METADATA
pymade-0.0.1.dist-info/RECORD
