Metadata-Version: 2.1
Name: pymade
Version: 0.0.1
Summary: Pymaker, the better `make`
Home-page: https://pymaker.readthedocs.io/en/latest/
Author: Pradhyum R
Author-email: drpradhyum2016@outlook.com
Classifier: License :: OSI Approved :: MIT License
Project-URL: Documentation, https://pymaker.readthedocs.io/en/latest/
Project-URL: Source-Code, https://github.com/techieji/Pymaker
